{
    "version": "1.62.0",
    "description": "A wrapper for Dart Sass that implements the compiler side of the Embedded Sass protocol",
    "homepage": "https://github.com/sass/dart-sass-embedded",
    "license": "MIT",
    "architecture": {
        "32bit": {
            "url": "https://github.com/sass/dart-sass-embedded/releases/download/1.56.1/sass_embedded-1.56.1-windows-ia32.zip",
            "hash": ""
        },
        "64bit": {
            "url": "https://github.com/sass/dart-sass-embedded/releases/download/1.62.0/sass_embedded-1.62.0-windows-ia32.zip",
            "hash": "cecb21ad5f4f46f15bc8dc2b7ff68b178979d977065babfcb5057024ba0918dd"
        }
    },
    "bin": "sass_embedded\\dart-sass-embedded.bat",
    "checkver": {
        "github": "https://github.com/sass/dart-sass-embedded"
    },
    "autoupdate": {
        "architecture": {
            "64bit": {
                "url": "https://github.com/sass/dart-sass-embedded/releases/download/$version/sass_embedded-$version-windows-ia32.zip"
            },
            "arm64": {
                "url": "https://github.com/sass/dart-sass-embedded/releases/download/$version/sass_embedded-$version-windows-x64.zip"
            }
        }
    }
}
